server/__init__.py
server/main.py
instant_json_server-0.1.2.dist-info/METADATA
instant_json_server-0.1.2.dist-info/WHEEL
instant_json_server-0.1.2.dist-info/entry_points.txt
instant_json_server-0.1.2.dist-info/top_level.txt
instant_json_server-0.1.2.dist-info/RECORD
